allvissone/__init__.py
allvissone/allvissone.py
allvissone-0.1.1.dist-info/LICENCE
allvissone-0.1.1.dist-info/METADATA
allvissone-0.1.1.dist-info/WHEEL
allvissone-0.1.1.dist-info/top_level.txt
allvissone-0.1.1.dist-info/zip-safe
allvissone-0.1.1.dist-info/RECORD
